{
  "session_id": "session_20260219_171612_1fcf5c",
  "events": [
    {
      "timestamp": "2026-02-19T17:16:12.911873",
      "event_type": "session_start",
      "data": {
        "session_id": "session_20260219_171612_1fcf5c"
      },
      "explanation": "Audit logging session started",
      "session_id": "session_20260219_171612_1fcf5c",
      "strategy_name": ""
    },
    {
      "timestamp": "2026-02-19T17:16:12.914260",
      "event_type": "session_start",
      "data": {
        "data_paths": [
          "data\\raw\\btcusdt_1m.csv"
        ],
        "timeframes": [
          "5m"
        ],
        "strategies": [
          "rsi_mean_reversion"
        ]
      },
      "explanation": "Starting full research pipeline",
      "session_id": "session_20260219_171612_1fcf5c",
      "strategy_name": ""
    },
    {
      "timestamp": "2026-02-19T17:16:12.933792",
      "event_type": "session_end",
      "data": {
        "session_id": "session_20260219_171612_1fcf5c",
        "total_events": 2,
        "total_signals": 0,
        "total_optimizations": 0,
        "total_parameter_changes": 0,
        "event_types": {
          "parameter_change": 0,
          "optimization_start": 0,
          "optimization_end": 0,
          "parameter_reset": 0,
          "signal_generated": 0,
          "signal_executed": 0,
          "signal_rejected": 0,
          "position_opened": 0,
          "position_closed": 0,
          "position_modified": 0,
          "condition_detected": 0,
          "failure_detected": 0,
          "regime_change": 0,
          "session_start": 2,
          "session_end": 0,
          "error": 0,
          "warning": 0
        },
        "strategies": []
      },
      "explanation": "Audit logging session ended",
      "session_id": "session_20260219_171612_1fcf5c",
      "strategy_name": ""
    }
  ],
  "signals": [],
  "optimizations": [],
  "parameters": []
}